dashport/__init__.py
dashport/borders.py
dashport/characters.py
dashport/colors.py
dashport/dash.py
dashport/layout.py
dashport/prompt.py
dashport/run.py
dashport/widgets.py
dashport/resources/__init__.py
dashport/resources/block_elements_table.json
dashport/resources/box_drawing_table.json
dashport-0.7.8.dist-info/METADATA
dashport-0.7.8.dist-info/WHEEL
dashport-0.7.8.dist-info/top_level.txt
dashport-0.7.8.dist-info/RECORD
