Metadata-Version: 2.1
Name: dashport
Version: 0.7.8
Summary: Dashport curses wrapper for Python
Home-page: https://github.com/numbertheory/dashport
Author: JP Etcheber
Author-email: jetcheber@gmail.com
